cccd/DataDescription.py
cccd/DataSet.py
cccd/__init__.py
cccd/common.py
cccd/format.py
cccd/metadata.py
cccd-0.1.1.dist-info/LICENSE
cccd-0.1.1.dist-info/METADATA
cccd-0.1.1.dist-info/WHEEL
cccd-0.1.1.dist-info/top_level.txt
cccd-0.1.1.dist-info/RECORD
