Metadata-Version: 2.1
Name: cccd
Version: 0.1.1
Summary: Generate csv files with descriptions of the data in a header
Author-email: Wojciech Sadowski <wojciech1sadowski@gmail.com>
License: MIT License
Project-URL: Homepage, https://github.com/szynka12/cccd
Keywords: metadata,data documentation
Classifier: License :: OSI Approved :: MIT License
Classifier: Programming Language :: Python
Classifier: Programming Language :: Python :: 3
Requires-Python: >=3.11
License-File: LICENSE
Requires-Dist: polars
Provides-Extra: dev
Requires-Dist: bumpver ; extra == 'dev'
Requires-Dist: pip-tools ; extra == 'dev'
